colour_filter/__init__.py
colour_filter/__main__.py
colour_filter-1.1.2.dist-info/METADATA
colour_filter-1.1.2.dist-info/WHEEL
colour_filter-1.1.2.dist-info/entry_points.txt
colour_filter-1.1.2.dist-info/top_level.txt
colour_filter-1.1.2.dist-info/RECORD
