Metadata-Version: 2.1
Name: colour-filter
Version: 1.1.2
Summary: The colour-filter command reads lines from it's input, colours parts of the line and prints the result on it's output
Author-email: Barry Scott <barry@barrys-emacs.org>
License: Apache-2.0
Project-URL: Homepage, https://github.com/barry-scott/CLI-tools
Project-URL: Bug Tracker, https://github.com/barry-scott/CLI-tools/issues
Keywords: development
Classifier: Intended Audience :: End Users/Desktop
Classifier: Topic :: Utilities
Classifier: Environment :: Console
Classifier: Programming Language :: Python :: 3
Requires-Python: >=3.10
Requires-Dist: colour-text
